bulletins/__init__.py
bulletins-0.1.0.dist-info/METADATA
bulletins-0.1.0.dist-info/WHEEL
bulletins-0.1.0.dist-info/entry_points.txt
bulletins-0.1.0.dist-info/RECORD
