Metadata-Version: 2.4
Name: bulletins
Version: 0.1.0
Summary: Modular changelogs using Markdown bulletins
Author-email: Aleix Pinardell <aleixpinardell@gmail.com>
License: MIT
Keywords: changelog
Requires-Python: >=3.8
